vlibras_deeplearning/VERSION
vlibras_deeplearning/__init__.py
vlibras_deeplearning/deep_translation.py
vlibras_deeplearning/model_utils.py
vlibras_deeplearning-1.0.9.dist-info/METADATA
vlibras_deeplearning-1.0.9.dist-info/RECORD
vlibras_deeplearning-1.0.9.dist-info/WHEEL
vlibras_deeplearning-1.0.9.dist-info/top_level.txt
