Metadata-Version: 2.1
Name: vlibras-deeplearning
Version: 1.0.9
Summary: VLibras (LAViD-UFPB) neural translation module for translating brazilian portuguese to LIBRAS.
Home-page: http://www.vlibras.gov.br/
Author: LAViD-UFPB
Author-email: vlibras@lavid.ufpb.br
License: UNKNOWN
Platform: UNKNOWN
Classifier: License :: OSI Approved :: GNU Lesser General Public License v3 (LGPLv3)
Classifier: Operating System :: POSIX :: Linux
Classifier: Operating System :: Microsoft :: Windows
Classifier: Programming Language :: Python :: 3
Classifier: Programming Language :: Python :: 3.5
Classifier: Programming Language :: Python :: 3.6
Classifier: Development Status :: 5 - Production/Stable
Classifier: Topic :: Text Processing :: Linguistic
Classifier: Natural Language :: Portuguese (Brazilian)
Requires-Dist: fairseq
Requires-Dist: subword-nmt
Requires-Dist: torch
